{
  "star-alliance": {
    "name": "Star Alliance",
    "founded": 1997,
    "members": ["LH","UA","AC","SQ","NH","TG","TK","BR","OZ","LX","OS","SN","LO","TP","ET","CA","ZH","SA","CM","MS","AV","NZ","AI","OU","A3","AZ"],
    "hubs": ["FRA","MUC","ORD","EWR","YYZ","SIN","NRT","BKK","IST"],
    "lastVerified": "2026-05-18",
    "source": "https://en.wikipedia.org/wiki/Star_Alliance (verified 2026-05-18; official site staralliance.com returned 403)"
  },
  "oneworld": {
    "name": "Oneworld",
    "founded": 1999,
    "members": ["AA","BA","CX","QF","JL","IB","AY","QR","RJ","UL","MH","AT","AS","FJ","WY","HA"],
    "hubs": ["LHR","DFW","HKG","SYD","HND","MAD","HEL","DOH"],
    "lastVerified": "2026-05-18",
    "source": "https://www.oneworld.com/member-airlines + https://en.wikipedia.org/wiki/Oneworld (verified 2026-05-18)"
  },
  "skyteam": {
    "name": "SkyTeam",
    "founded": 2000,
    "members": ["DL","AF","KL","KE","KQ","UX","RO","SV","CI","MU","VN","VS","ME","GA","AR","AM","MF","SK"],
    "hubs": ["ATL","CDG","AMS","ICN","TPE","HAN"],
    "lastVerified": "2026-05-18",
    "source": "https://en.wikipedia.org/wiki/SkyTeam (verified 2026-05-18; official site skyteam.com returned 403)"
  }
}
